{
    "description": "",
    "tags": [
        {
            "id": 4751503,
            "tagId": 20959,
            "name": "caption",
            "value": "A refrigerator in a kitchen covered in papers, magnets and pictures.",
            "labelerLogin": "az@datasetninja.com",
            "createdAt": "2023-09-20T10:47:15.205Z",
            "updatedAt": "2023-09-20T10:47:15.205Z"
        },
        {
            "id": 4751504,
            "tagId": 20959,
            "name": "caption",
            "value": "A white refrigerator in a very small kitchen.",
            "labelerLogin": "az@datasetninja.com",
            "createdAt": "2023-09-20T10:47:15.205Z",
            "updatedAt": "2023-09-20T10:47:15.205Z"
        },
        {
            "id": 4751505,
            "tagId": 20959,
            "name": "caption",
            "value": "A fridge with stickers and wine bottles on top of it.",
            "labelerLogin": "az@datasetninja.com",
            "createdAt": "2023-09-20T10:47:15.205Z",
            "updatedAt": "2023-09-20T10:47:15.205Z"
        },
        {
            "id": 4751506,
            "tagId": 20959,
            "name": "caption",
            "value": "A refrigerator covered in magnets, paper and wine bottles.",
            "labelerLogin": "az@datasetninja.com",
            "createdAt": "2023-09-20T10:47:15.205Z",
            "updatedAt": "2023-09-20T10:47:15.205Z"
        },
        {
            "id": 4751507,
            "tagId": 20959,
            "name": "caption",
            "value": "A refrigerator with pictures and magnets attached to it. ",
            "labelerLogin": "az@datasetninja.com",
            "createdAt": "2023-09-20T10:47:15.205Z",
            "updatedAt": "2023-09-20T10:47:15.205Z"
        }
    ],
    "size": {
        "height": 640,
        "width": 480
    },
    "objects": [
        {
            "id": 46910596,
            "classId": 6461802,
            "description": "",
            "geometryType": "polygon",
            "labelerLogin": "az@datasetninja.com",
            "createdAt": "2023-09-20T10:47:15.214Z",
            "updatedAt": "2023-09-20T10:47:15.214Z",
            "tags": [],
            "classTitle": "bottle",
            "points": {
                "exterior": [
                    [
                        89,
                        176
                    ],
                    [
                        86,
                        172
                    ],
                    [
                        86,
                        126
                    ],
                    [
                        90,
                        119
                    ],
                    [
                        91,
                        118
                    ],
                    [
                        92,
                        110
                    ],
                    [
                        88,
                        104
                    ],
                    [
                        89,
                        88
                    ],
                    [
                        101,
                        81
                    ],
                    [
                        101,
                        78
                    ],
                    [
                        100,
                        77
                    ],
                    [
                        100,
                        69
                    ],
                    [
                        102,
                        67
                    ],
                    [
                        102,
                        63
                    ],
                    [
                        104,
                        60
                    ],
                    [
                        110,
                        60
                    ],
                    [
                        113,
                        62
                    ],
                    [
                        113,
                        67
                    ],
                    [
                        115,
                        69
                    ],
                    [
                        114,
                        73
                    ],
                    [
                        114,
                        80
                    ],
                    [
                        112,
                        81
                    ],
                    [
                        123,
                        91
                    ],
                    [
                        123,
                        108
                    ],
                    [
                        119,
                        112
                    ],
                    [
                        119,
                        123
                    ],
                    [
                        122,
                        127
                    ],
                    [
                        122,
                        167
                    ]
                ],
                "interior": []
            }
        },
        {
            "id": 46910595,
            "classId": 6461802,
            "description": "",
            "geometryType": "rectangle",
            "labelerLogin": "az@datasetninja.com",
            "createdAt": "2023-09-20T10:47:15.214Z",
            "updatedAt": "2023-09-20T10:47:15.214Z",
            "tags": [],
            "classTitle": "bottle",
            "points": {
                "exterior": [
                    [
                        86,
                        60
                    ],
                    [
                        123,
                        176
                    ]
                ],
                "interior": []
            }
        },
        {
            "id": 46910594,
            "classId": 6461802,
            "description": "",
            "geometryType": "polygon",
            "labelerLogin": "az@datasetninja.com",
            "createdAt": "2023-09-20T10:47:15.214Z",
            "updatedAt": "2023-09-20T10:47:15.214Z",
            "tags": [],
            "classTitle": "bottle",
            "points": {
                "exterior": [
                    [
                        156,
                        30
                    ],
                    [
                        154,
                        53
                    ],
                    [
                        136,
                        74
                    ],
                    [
                        140,
                        172
                    ],
                    [
                        190,
                        168
                    ],
                    [
                        183,
                        70
                    ],
                    [
                        164,
                        59
                    ],
                    [
                        165,
                        27
                    ]
                ],
                "interior": []
            }
        },
        {
            "id": 46910593,
            "classId": 6461802,
            "description": "",
            "geometryType": "rectangle",
            "labelerLogin": "az@datasetninja.com",
            "createdAt": "2023-09-20T10:47:15.213Z",
            "updatedAt": "2023-09-20T10:47:15.213Z",
            "tags": [],
            "classTitle": "bottle",
            "points": {
                "exterior": [
                    [
                        136,
                        27
                    ],
                    [
                        190,
                        172
                    ]
                ],
                "interior": []
            }
        },
        {
            "id": 46910592,
            "classId": 6461802,
            "description": "",
            "geometryType": "polygon",
            "labelerLogin": "az@datasetninja.com",
            "createdAt": "2023-09-20T10:47:15.213Z",
            "updatedAt": "2023-09-20T10:47:15.213Z",
            "tags": [],
            "classTitle": "bottle",
            "points": {
                "exterior": [
                    [
                        218,
                        67
                    ],
                    [
                        231,
                        68
                    ],
                    [
                        232,
                        110
                    ],
                    [
                        235,
                        126
                    ],
                    [
                        238,
                        143
                    ],
                    [
                        239,
                        170
                    ],
                    [
                        216,
                        169
                    ],
                    [
                        216,
                        92
                    ],
                    [
                        218,
                        76
                    ]
                ],
                "interior": []
            }
        },
        {
            "id": 46910591,
            "classId": 6461802,
            "description": "",
            "geometryType": "rectangle",
            "labelerLogin": "az@datasetninja.com",
            "createdAt": "2023-09-20T10:47:15.213Z",
            "updatedAt": "2023-09-20T10:47:15.213Z",
            "tags": [],
            "classTitle": "bottle",
            "points": {
                "exterior": [
                    [
                        216,
                        67
                    ],
                    [
                        239,
                        170
                    ]
                ],
                "interior": []
            }
        },
        {
            "id": 46910590,
            "classId": 6461802,
            "description": "",
            "geometryType": "polygon",
            "labelerLogin": "az@datasetninja.com",
            "createdAt": "2023-09-20T10:47:15.213Z",
            "updatedAt": "2023-09-20T10:47:15.213Z",
            "tags": [],
            "classTitle": "bottle",
            "points": {
                "exterior": [
                    [
                        126,
                        165
                    ],
                    [
                        129,
                        129
                    ],
                    [
                        129,
                        92
                    ],
                    [
                        129,
                        83
                    ],
                    [
                        139,
                        81
                    ],
                    [
                        140,
                        151
                    ],
                    [
                        140,
                        166
                    ]
                ],
                "interior": []
            }
        },
        {
            "id": 46910589,
            "classId": 6461802,
            "description": "",
            "geometryType": "rectangle",
            "labelerLogin": "az@datasetninja.com",
            "createdAt": "2023-09-20T10:47:15.212Z",
            "updatedAt": "2023-09-20T10:47:15.212Z",
            "tags": [],
            "classTitle": "bottle",
            "points": {
                "exterior": [
                    [
                        126,
                        81
                    ],
                    [
                        140,
                        166
                    ]
                ],
                "interior": []
            }
        },
        {
            "id": 46910588,
            "classId": 6461835,
            "description": "",
            "geometryType": "polygon",
            "labelerLogin": "az@datasetninja.com",
            "createdAt": "2023-09-20T10:47:15.211Z",
            "updatedAt": "2023-09-20T10:47:15.211Z",
            "tags": [],
            "classTitle": "refrigerator",
            "points": {
                "exterior": [
                    [
                        127,
                        175
                    ],
                    [
                        358,
                        178
                    ],
                    [
                        402,
                        186
                    ],
                    [
                        387,
                        445
                    ],
                    [
                        372,
                        624
                    ],
                    [
                        179,
                        629
                    ],
                    [
                        145,
                        624
                    ],
                    [
                        137,
                        463
                    ],
                    [
                        137,
                        305
                    ]
                ],
                "interior": []
            }
        },
        {
            "id": 46910587,
            "classId": 6461835,
            "description": "",
            "geometryType": "rectangle",
            "labelerLogin": "az@datasetninja.com",
            "createdAt": "2023-09-20T10:47:15.211Z",
            "updatedAt": "2023-09-20T10:47:15.211Z",
            "tags": [],
            "classTitle": "refrigerator",
            "points": {
                "exterior": [
                    [
                        127,
                        175
                    ],
                    [
                        402,
                        629
                    ]
                ],
                "interior": []
            }
        },
        {
            "id": 46910586,
            "classId": 6461802,
            "description": "",
            "geometryType": "polygon",
            "labelerLogin": "az@datasetninja.com",
            "createdAt": "2023-09-20T10:47:15.210Z",
            "updatedAt": "2023-09-20T10:47:15.210Z",
            "tags": [],
            "classTitle": "bottle",
            "points": {
                "exterior": [
                    [
                        253,
                        78
                    ],
                    [
                        251,
                        87
                    ],
                    [
                        248,
                        90
                    ],
                    [
                        250,
                        112
                    ],
                    [
                        263,
                        109
                    ],
                    [
                        263,
                        88
                    ],
                    [
                        263,
                        86
                    ],
                    [
                        262,
                        85
                    ],
                    [
                        262,
                        80
                    ],
                    [
                        262,
                        75
                    ]
                ],
                "interior": []
            }
        },
        {
            "id": 46910585,
            "classId": 6461802,
            "description": "",
            "geometryType": "rectangle",
            "labelerLogin": "az@datasetninja.com",
            "createdAt": "2023-09-20T10:47:15.210Z",
            "updatedAt": "2023-09-20T10:47:15.210Z",
            "tags": [],
            "classTitle": "bottle",
            "points": {
                "exterior": [
                    [
                        248,
                        75
                    ],
                    [
                        263,
                        112
                    ]
                ],
                "interior": []
            }
        },
        {
            "id": 46910584,
            "classId": 6461832,
            "description": "",
            "geometryType": "polygon",
            "labelerLogin": "az@datasetninja.com",
            "createdAt": "2023-09-20T10:47:15.209Z",
            "updatedAt": "2023-09-20T10:47:15.209Z",
            "tags": [],
            "classTitle": "oven",
            "points": {
                "exterior": [
                    [
                        0,
                        456
                    ],
                    [
                        13,
                        455
                    ],
                    [
                        44,
                        611
                    ],
                    [
                        44,
                        639
                    ],
                    [
                        0,
                        639
                    ]
                ],
                "interior": []
            }
        },
        {
            "id": 46910583,
            "classId": 6461832,
            "description": "",
            "geometryType": "rectangle",
            "labelerLogin": "az@datasetninja.com",
            "createdAt": "2023-09-20T10:47:15.209Z",
            "updatedAt": "2023-09-20T10:47:15.209Z",
            "tags": [],
            "classTitle": "oven",
            "points": {
                "exterior": [
                    [
                        0,
                        455
                    ],
                    [
                        44,
                        639
                    ]
                ],
                "interior": []
            }
        },
        {
            "id": 46910582,
            "classId": 6461802,
            "description": "",
            "geometryType": "polygon",
            "labelerLogin": "az@datasetninja.com",
            "createdAt": "2023-09-20T10:47:15.209Z",
            "updatedAt": "2023-09-20T10:47:15.209Z",
            "tags": [],
            "classTitle": "bottle",
            "points": {
                "exterior": [
                    [
                        207,
                        166
                    ],
                    [
                        191,
                        166
                    ],
                    [
                        187,
                        106
                    ],
                    [
                        184,
                        74
                    ],
                    [
                        188,
                        69
                    ],
                    [
                        189,
                        57
                    ],
                    [
                        190,
                        33
                    ],
                    [
                        190,
                        30
                    ],
                    [
                        191,
                        29
                    ],
                    [
                        192,
                        16
                    ],
                    [
                        203,
                        15
                    ],
                    [
                        203,
                        30
                    ],
                    [
                        205,
                        31
                    ],
                    [
                        205,
                        54
                    ],
                    [
                        205,
                        68
                    ],
                    [
                        210,
                        74
                    ],
                    [
                        210,
                        94
                    ],
                    [
                        211,
                        98
                    ],
                    [
                        210,
                        146
                    ],
                    [
                        210,
                        150
                    ],
                    [
                        209,
                        166
                    ]
                ],
                "interior": []
            }
        },
        {
            "id": 46910581,
            "classId": 6461802,
            "description": "",
            "geometryType": "rectangle",
            "labelerLogin": "az@datasetninja.com",
            "createdAt": "2023-09-20T10:47:15.208Z",
            "updatedAt": "2023-09-20T10:47:15.208Z",
            "tags": [],
            "classTitle": "bottle",
            "points": {
                "exterior": [
                    [
                        184,
                        15
                    ],
                    [
                        211,
                        166
                    ]
                ],
                "interior": []
            }
        },
        {
            "id": 46910580,
            "classId": 6461802,
            "description": "",
            "geometryType": "polygon",
            "labelerLogin": "az@datasetninja.com",
            "createdAt": "2023-09-20T10:47:15.208Z",
            "updatedAt": "2023-09-20T10:47:15.208Z",
            "tags": [],
            "classTitle": "bottle",
            "points": {
                "exterior": [
                    [
                        240,
                        169
                    ],
                    [
                        236,
                        128
                    ],
                    [
                        232,
                        107
                    ],
                    [
                        230,
                        70
                    ],
                    [
                        227,
                        65
                    ],
                    [
                        228,
                        57
                    ],
                    [
                        240,
                        58
                    ],
                    [
                        242,
                        78
                    ],
                    [
                        248,
                        106
                    ],
                    [
                        248,
                        114
                    ],
                    [
                        245,
                        128
                    ],
                    [
                        248,
                        149
                    ],
                    [
                        250,
                        166
                    ],
                    [
                        241,
                        168
                    ]
                ],
                "interior": []
            }
        },
        {
            "id": 46910579,
            "classId": 6461802,
            "description": "",
            "geometryType": "rectangle",
            "labelerLogin": "az@datasetninja.com",
            "createdAt": "2023-09-20T10:47:15.208Z",
            "updatedAt": "2023-09-20T10:47:15.208Z",
            "tags": [],
            "classTitle": "bottle",
            "points": {
                "exterior": [
                    [
                        227,
                        57
                    ],
                    [
                        250,
                        169
                    ]
                ],
                "interior": []
            }
        },
        {
            "id": 46910578,
            "classId": 6461802,
            "description": "",
            "geometryType": "polygon",
            "labelerLogin": "az@datasetninja.com",
            "createdAt": "2023-09-20T10:47:15.206Z",
            "updatedAt": "2023-09-20T10:47:15.206Z",
            "tags": [],
            "classTitle": "bottle",
            "points": {
                "exterior": [
                    [
                        189,
                        44
                    ],
                    [
                        179,
                        44
                    ],
                    [
                        179,
                        58
                    ],
                    [
                        189,
                        58
                    ],
                    [
                        189,
                        44
                    ]
                ],
                "interior": []
            }
        },
        {
            "id": 46910577,
            "classId": 6461802,
            "description": "",
            "geometryType": "rectangle",
            "labelerLogin": "az@datasetninja.com",
            "createdAt": "2023-09-20T10:47:15.206Z",
            "updatedAt": "2023-09-20T10:47:15.206Z",
            "tags": [],
            "classTitle": "bottle",
            "points": {
                "exterior": [
                    [
                        179,
                        44
                    ],
                    [
                        189,
                        58
                    ]
                ],
                "interior": []
            }
        }
    ]
}